propertia/client.py
propertia-0.1.5.dist-info/METADATA
propertia-0.1.5.dist-info/WHEEL
propertia-0.1.5.dist-info/top_level.txt
propertia-0.1.5.dist-info/RECORD
