Metadata-Version: 2.1
Name: propertia
Version: 0.1.5
Summary: The Propertia SDK helps users integrate easily with the SmartScore services
Author: SearchSmartly
License: MIT
Requires-Python: >=3.8
Requires-Dist: httpx ==0.25.2
Provides-Extra: test
Requires-Dist: flake8 ; extra == 'test'
Requires-Dist: pytest ; extra == 'test'
